poselib/__init__.py
poselib_v2-0.0.1.dist-info/LICENSE
poselib_v2-0.0.1.dist-info/METADATA
poselib_v2-0.0.1.dist-info/WHEEL
poselib_v2-0.0.1.dist-info/top_level.txt
poselib_v2-0.0.1.dist-info/RECORD
