Metadata-Version: 2.1
Name: poselib-v2
Version: 0.0.1
Summary: Library for loading, manipulating, and retargeting skeleton poses and motions.
Home-page: https://github.com/T-K-233/PoseLib
Author: -T.K.-
Author-email: t_k_233@outlook.email
Classifier: Programming Language :: Python :: 3
Classifier: License :: OSI Approved :: MIT License
Classifier: Operating System :: OS Independent
Requires-Python: >=3.8
License-File: LICENSE
